{
  "timestamp": "2025-10-30T14:04:57.861727",
  "repository": "tenstorrent/tt-metal",
  "branch": "main",
  "total_prs": 2,
  "entries": [
    {
      "position": 1,
      "state": "AWAITING_CHECKS",
      "pr_number": 31431,
      "pr_title": "Fix CCL test on T3K profiler regression nightly",
      "pr_url": "https://github.com/tenstorrent/tt-metal/pull/31431",
      "author": "mo-tenstorrent",
      "enqueued_at": "2025-10-30T13:27:11Z",
      "estimated_time_to_merge_seconds": 6239,
      "time_in_queue": "37 minutes",
      "commit": {
        "sha": "4495b3c408bce099b572bb178e976570461ae284",
        "url": "https://github.com/tenstorrent/tt-metal/commit/4495b3c408bce099b572bb178e976570461ae284"
      },
      "ci_status": {
        "overall_state": "PENDING",
        "ci_started_at": "2025-10-30T13:27:35Z",
        "total_checks": 100,
        "running": 6,
        "completed": 92,
        "queued": 2,
        "checks": [
          {
            "name": "static-checks / find-changed-files",
            "status": "COMPLETED",
            "conclusion": "SUCCESS",
            "started_at": "2025-10-30T13:27:36Z",
            "completed_at": "2025-10-30T13:29:22Z",
            "details_url": "https://github.com/tenstorrent/tt-metal/actions/runs/18942222369/job/54083739795"
          },
          {
            "name": "asan-build / build-docker-image / check-docker-images",
            "status": "COMPLETED",
            "conclusion": "SUCCESS",
            "started_at": "2025-10-30T13:27:46Z",
            "completed_at": "2025-10-30T13:28:01Z",
            "details_url": "https://github.com/tenstorrent/tt-metal/actions/runs/18942222283/job/54083754857"
          },
          {
            "name": "find-changed-files",
            "status": "COMPLETED",
            "conclusion": "SUCCESS",
            "started_at": "2025-10-30T13:27:36Z",
            "completed_at": "2025-10-30T13:28:30Z",
            "details_url": "https://github.com/tenstorrent/tt-metal/actions/runs/18942222248/job/54083736401"
          },
          {
            "name": "asan-build / build-docker-image / \ud83d\udc33\ufe0f Build images",
            "status": "COMPLETED",
            "conclusion": "SKIPPED",
            "started_at": "2025-10-30T13:28:03Z",
            "completed_at": "2025-10-30T13:28:03Z",
            "details_url": "https://github.com/tenstorrent/tt-metal/actions/runs/18942222283/job/54083792460"
          },
          {
            "name": "static-checks / Run Pre-commit Hooks",
            "status": "COMPLETED",
            "conclusion": "SUCCESS",
            "started_at": "2025-10-30T13:27:37Z",
            "completed_at": "2025-10-30T13:28:24Z",
            "details_url": "https://github.com/tenstorrent/tt-metal/actions/runs/18942222369/job/54083739689"
          },
          {
            "name": "Run Pre-commit Hooks",
            "status": "COMPLETED",
            "conclusion": "SUCCESS",
            "started_at": "2025-10-30T13:27:38Z",
            "completed_at": "2025-10-30T13:28:23Z",
            "details_url": "https://github.com/tenstorrent/tt-metal/actions/runs/18942222248/job/54083736353"
          },
          {
            "name": "asan-build / build-docker-image / \ud83d\udd04 Update latest tag",
            "status": "COMPLETED",
            "conclusion": "SKIPPED",
            "started_at": "2025-10-30T13:28:03Z",
            "completed_at": "2025-10-30T13:28:03Z",
            "details_url": "https://github.com/tenstorrent/tt-metal/actions/runs/18942222283/job/54083792491"
          },
          {
            "name": "static-checks / check-black",
            "status": "COMPLETED",
            "conclusion": "SUCCESS",
            "started_at": "2025-10-30T13:27:37Z",
            "completed_at": "2025-10-30T13:27:39Z",
            "details_url": "https://github.com/tenstorrent/tt-metal/actions/runs/18942222369/job/54083739717"
          },
          {
            "name": "check-black",
            "status": "COMPLETED",
            "conclusion": "SUCCESS",
            "started_at": "2025-10-30T13:27:36Z",
            "completed_at": "2025-10-30T13:27:40Z",
            "details_url": "https://github.com/tenstorrent/tt-metal/actions/runs/18942222248/job/54083736463"
          },
          {
            "name": "static-checks / check-spdx-licenses",
            "status": "COMPLETED",
            "conclusion": "SUCCESS",
            "started_at": "2025-10-30T13:27:36Z",
            "completed_at": "2025-10-30T13:28:41Z",
            "details_url": "https://github.com/tenstorrent/tt-metal/actions/runs/18942222369/job/54083739846"
          },
          {
            "name": "asan-build / \ud83d\udee0\ufe0f Build ASanCoverage ubuntu 22.04",
            "status": "COMPLETED",
            "conclusion": "SUCCESS",
            "started_at": "2025-10-30T13:28:43Z",
            "completed_at": "2025-10-30T14:03:21Z",
            "details_url": "https://github.com/tenstorrent/tt-metal/actions/runs/18942222283/job/54083805219"
          },
          {
            "name": "check-spdx-licenses",
            "status": "COMPLETED",
            "conclusion": "SUCCESS",
            "started_at": "2025-10-30T13:27:35Z",
            "completed_at": "2025-10-30T13:28:37Z",
            "details_url": "https://github.com/tenstorrent/tt-metal/actions/runs/18942222248/job/54083736441"
          },
          {
            "name": "asan-build / \ud83d\udc0d Build wheel (Python ${{ inputs.version == '22.04' && '3.10' || '3.12' }})",
            "status": "COMPLETED",
            "conclusion": "SKIPPED",
            "started_at": "2025-10-30T13:28:10Z",
            "completed_at": "2025-10-30T13:28:10Z",
            "details_url": "https://github.com/tenstorrent/tt-metal/actions/runs/18942222283/job/54083803961"
          },
          {
            "name": "static-checks / check-metal-kernel-count",
            "status": "COMPLETED",
            "conclusion": "SUCCESS",
            "started_at": "2025-10-30T13:27:35Z",
            "completed_at": "2025-10-30T13:27:45Z",
            "details_url": "https://github.com/tenstorrent/tt-metal/actions/runs/18942222369/job/54083739855"
          },
          {
            "name": "check-metal-kernel-count",
            "status": "COMPLETED",
            "conclusion": "SUCCESS",
            "started_at": "2025-10-30T13:27:36Z",
            "completed_at": "2025-10-30T13:27:45Z",
            "details_url": "https://github.com/tenstorrent/tt-metal/actions/runs/18942222248/job/54083736541"
          },
          {
            "name": "static-checks / check-doc",
            "status": "COMPLETED",
            "conclusion": "SUCCESS",
            "started_at": "2025-10-30T13:27:36Z",
            "completed_at": "2025-10-30T13:28:01Z",
            "details_url": "https://github.com/tenstorrent/tt-metal/actions/runs/18942222369/job/54083739845"
          },
          {
            "name": "find-changed-files",
            "status": "COMPLETED",
            "conclusion": "SUCCESS",
            "started_at": "2025-10-30T13:27:43Z",
            "completed_at": "2025-10-30T13:28:31Z",
            "details_url": "https://github.com/tenstorrent/tt-metal/actions/runs/18942222283/job/54083750758"
          },
          {
            "name": "check-doc",
            "status": "COMPLETED",
            "conclusion": "SUCCESS",
            "started_at": "2025-10-30T13:27:36Z",
            "completed_at": "2025-10-30T13:28:05Z",
            "details_url": "https://github.com/tenstorrent/tt-metal/actions/runs/18942222248/job/54083736548"
          },
          {
            "name": "static-checks / check-forbidden-imports",
            "status": "COMPLETED",
            "conclusion": "SUCCESS",
            "started_at": "2025-10-30T13:27:37Z",
            "completed_at": "2025-10-30T13:27:45Z",
            "details_url": "https://github.com/tenstorrent/tt-metal/actions/runs/18942222369/job/54083739678"
          },
          {
            "name": "build / build-docker-image / check-docker-images",
            "status": "COMPLETED",
            "conclusion": "SUCCESS",
            "started_at": "2025-10-30T13:27:46Z",
            "completed_at": "2025-10-30T13:27:58Z",
            "details_url": "https://github.com/tenstorrent/tt-metal/actions/runs/18942222283/job/54083754819"
          },
          {
            "name": "check-forbidden-imports",
            "status": "COMPLETED",
            "conclusion": "SUCCESS",
            "started_at": "2025-10-30T13:27:35Z",
            "completed_at": "2025-10-30T13:27:45Z",
            "details_url": "https://github.com/tenstorrent/tt-metal/actions/runs/18942222248/job/54083736587"
          },
          {
            "name": "build / build-docker-image / \ud83d\udc33\ufe0f Build images",
            "status": "COMPLETED",
            "conclusion": "SKIPPED",
            "started_at": "2025-10-30T13:28:00Z",
            "completed_at": "2025-10-30T13:28:00Z",
            "details_url": "https://github.com/tenstorrent/tt-metal/actions/runs/18942222283/job/54083787780"
          },
          {
            "name": "static-checks / check-interleaved-addr-gen-usage",
            "status": "COMPLETED",
            "conclusion": "SUCCESS",
            "started_at": "2025-10-30T13:27:38Z",
            "completed_at": "2025-10-30T13:28:20Z",
            "details_url": "https://github.com/tenstorrent/tt-metal/actions/runs/18942222369/job/54083739786"
          },
          {
            "name": "check-interleaved-addr-gen-usage",
            "status": "COMPLETED",
            "conclusion": "SUCCESS",
            "started_at": "2025-10-30T13:27:37Z",
            "completed_at": "2025-10-30T13:28:15Z",
            "details_url": "https://github.com/tenstorrent/tt-metal/actions/runs/18942222248/job/54083736571"
          },
          {
            "name": "build / build-docker-image / \ud83d\udd04 Update latest tag",
            "status": "COMPLETED",
            "conclusion": "SKIPPED",
            "started_at": "2025-10-30T13:28:00Z",
            "completed_at": "2025-10-30T13:28:00Z",
            "details_url": "https://github.com/tenstorrent/tt-metal/actions/runs/18942222283/job/54083787729"
          },
          {
            "name": "static-checks / check-sweeps-workflow",
            "status": "COMPLETED",
            "conclusion": "SUCCESS",
            "started_at": "2025-10-30T13:27:36Z",
            "completed_at": "2025-10-30T13:27:50Z",
            "details_url": "https://github.com/tenstorrent/tt-metal/actions/runs/18942222369/job/54083739750"
          },
          {
            "name": "check-sweeps-workflow",
            "status": "COMPLETED",
            "conclusion": "SUCCESS",
            "started_at": "2025-10-30T13:27:37Z",
            "completed_at": "2025-10-30T13:27:47Z",
            "details_url": "https://github.com/tenstorrent/tt-metal/actions/runs/18942222248/job/54083736562"
          },
          {
            "name": "static-checks / cmake-version",
            "status": "COMPLETED",
            "conclusion": "SUCCESS",
            "started_at": "2025-10-30T13:27:36Z",
            "completed_at": "2025-10-30T13:32:18Z",
            "details_url": "https://github.com/tenstorrent/tt-metal/actions/runs/18942222369/job/54083739762"
          },
          {
            "name": "build / \ud83d\udee0\ufe0f Build Release ubuntu 22.04",
            "status": "COMPLETED",
            "conclusion": "SUCCESS",
            "started_at": "2025-10-30T13:28:43Z",
            "completed_at": "2025-10-30T13:47:05Z",
            "details_url": "https://github.com/tenstorrent/tt-metal/actions/runs/18942222283/job/54083791029"
          },
          {
            "name": "cmake-version",
            "status": "COMPLETED",
            "conclusion": "SUCCESS",
            "started_at": "2025-10-30T13:27:35Z",
            "completed_at": "2025-10-30T13:32:17Z",
            "details_url": "https://github.com/tenstorrent/tt-metal/actions/runs/18942222248/job/54083736575"
          },
          {
            "name": "static-checks / codeowners-validator",
            "status": "COMPLETED",
            "conclusion": "SUCCESS",
            "started_at": "2025-10-30T13:27:35Z",
            "completed_at": "2025-10-30T13:27:47Z",
            "details_url": "https://github.com/tenstorrent/tt-metal/actions/runs/18942222369/job/54083739684"
          },
          {
            "name": "build / \ud83d\udc0d Build wheel (Python 3.10)",
            "status": "COMPLETED",
            "conclusion": "SUCCESS",
            "started_at": "2025-10-30T13:28:43Z",
            "completed_at": "2025-10-30T13:46:37Z",
            "details_url": "https://github.com/tenstorrent/tt-metal/actions/runs/18942222283/job/54083791017"
          },
          {
            "name": "codeowners-validator",
            "status": "COMPLETED",
            "conclusion": "SUCCESS",
            "started_at": "2025-10-30T13:27:38Z",
            "completed_at": "2025-10-30T13:27:51Z",
            "details_url": "https://github.com/tenstorrent/tt-metal/actions/runs/18942222248/job/54083736638"
          },
          {
            "name": "docker-image",
            "status": "COMPLETED",
            "conclusion": "SKIPPED",
            "started_at": "2025-10-30T13:27:39Z",
            "completed_at": "2025-10-30T13:27:38Z",
            "details_url": "https://github.com/tenstorrent/tt-metal/actions/runs/18942222283/job/54083750072"
          },
          {
            "name": "static-checks / check-symlinks-valid",
            "status": "COMPLETED",
            "conclusion": "SUCCESS",
            "started_at": "2025-10-30T13:27:37Z",
            "completed_at": "2025-10-30T13:27:46Z",
            "details_url": "https://github.com/tenstorrent/tt-metal/actions/runs/18942222369/job/54083739777"
          },
          {
            "name": "check-symlinks-valid",
            "status": "COMPLETED",
            "conclusion": "SUCCESS",
            "started_at": "2025-10-30T13:27:35Z",
            "completed_at": "2025-10-30T13:27:45Z",
            "details_url": "https://github.com/tenstorrent/tt-metal/actions/runs/18942222248/job/54083736622"
          },
          {
            "name": "static-checks / check-docs-links",
            "status": "COMPLETED",
            "conclusion": "SKIPPED",
            "started_at": "2025-10-30T13:29:23Z",
            "completed_at": "2025-10-30T13:29:22Z",
            "details_url": "https://github.com/tenstorrent/tt-metal/actions/runs/18942222369/job/54083930965"
          },
          {
            "name": "check-docs-links",
            "status": "COMPLETED",
            "conclusion": "SKIPPED",
            "started_at": "2025-10-30T13:28:31Z",
            "completed_at": "2025-10-30T13:28:31Z",
            "details_url": "https://github.com/tenstorrent/tt-metal/actions/runs/18942222248/job/54083839832"
          },
          {
            "name": "code-analysis / determine-scan-type",
            "status": "COMPLETED",
            "conclusion": "SUCCESS",
            "started_at": "2025-10-30T13:27:37Z",
            "completed_at": "2025-10-30T13:28:19Z",
            "details_url": "https://github.com/tenstorrent/tt-metal/actions/runs/18942222369/job/54083739660"
          },
          {
            "name": "metalium-smoke-tests (N150-viommu) / smoke",
            "status": "QUEUED",
            "conclusion": null,
            "started_at": "2025-10-30T14:03:25Z",
            "completed_at": null,
            "details_url": "https://github.com/tenstorrent/tt-metal/actions/runs/18942222283/job/54087600293"
          },
          {
            "name": "code-analysis / build-docker-image / check-docker-images",
            "status": "COMPLETED",
            "conclusion": "SUCCESS",
            "started_at": "2025-10-30T13:27:36Z",
            "completed_at": "2025-10-30T13:27:46Z",
            "details_url": "https://github.com/tenstorrent/tt-metal/actions/runs/18942222369/job/54083740637"
          },
          {
            "name": "ttnn-smoke-tests (N150-viommu) / smoke",
            "status": "IN_PROGRESS",
            "conclusion": null,
            "started_at": "2025-10-30T14:04:39Z",
            "completed_at": null,
            "details_url": "https://github.com/tenstorrent/tt-metal/actions/runs/18942222283/job/54087600240"
          },
          {
            "name": "code-analysis / build-docker-image / \ud83d\udc33\ufe0f Build images",
            "status": "COMPLETED",
            "conclusion": "SKIPPED",
            "started_at": "2025-10-30T13:27:47Z",
            "completed_at": "2025-10-30T13:27:46Z",
            "details_url": "https://github.com/tenstorrent/tt-metal/actions/runs/18942222369/job/54083763338"
          },
          {
            "name": "code-analysis / build-docker-image / \ud83d\udd04 Update latest tag",
            "status": "COMPLETED",
            "conclusion": "SKIPPED",
            "started_at": "2025-10-30T13:27:47Z",
            "completed_at": "2025-10-30T13:27:46Z",
            "details_url": "https://github.com/tenstorrent/tt-metal/actions/runs/18942222369/job/54083763402"
          },
          {
            "name": "model-charts-sync",
            "status": "COMPLETED",
            "conclusion": "SKIPPED",
            "started_at": "2025-10-30T13:28:35Z",
            "completed_at": "2025-10-30T13:28:35Z",
            "details_url": "https://github.com/tenstorrent/tt-metal/actions/runs/18942222283/job/54083847095"
          },
          {
            "name": "code-analysis / \ud83e\udd16 Clang Tidy",
            "status": "IN_PROGRESS",
            "conclusion": null,
            "started_at": "2025-10-30T13:29:00Z",
            "completed_at": null,
            "details_url": "https://github.com/tenstorrent/tt-metal/actions/runs/18942222369/job/54083820429"
          },
          {
            "name": "build-tt-train",
            "status": "IN_PROGRESS",
            "conclusion": null,
            "started_at": "2025-10-30T13:52:05Z",
            "completed_at": null,
            "details_url": "https://github.com/tenstorrent/tt-metal/actions/runs/18942222283/job/54085822702"
          },
          {
            "name": "find-changes",
            "status": "COMPLETED",
            "conclusion": "SUCCESS",
            "started_at": "2025-10-30T13:27:37Z",
            "completed_at": "2025-10-30T13:28:28Z",
            "details_url": "https://github.com/tenstorrent/tt-metal/actions/runs/18942222369/job/54083739001"
          },
          {
            "name": "metalium-examples (N150-viommu) / sdk-examples",
            "status": "COMPLETED",
            "conclusion": "SUCCESS",
            "started_at": "2025-10-30T13:48:23Z",
            "completed_at": "2025-10-30T13:57:51Z",
            "details_url": "https://github.com/tenstorrent/tt-metal/actions/runs/18942222283/job/54085823385"
          },
          {
            "name": "ttnn-examples (N150-viommu) / sdk-examples",
            "status": "COMPLETED",
            "conclusion": "SUCCESS",
            "started_at": "2025-10-30T13:51:27Z",
            "completed_at": "2025-10-30T13:55:55Z",
            "details_url": "https://github.com/tenstorrent/tt-metal/actions/runs/18942222283/job/54085823515"
          },
          {
            "name": "build / build-docker-image / check-docker-images",
            "status": "COMPLETED",
            "conclusion": "SUCCESS",
            "started_at": "2025-10-30T13:28:34Z",
            "completed_at": "2025-10-30T13:28:47Z",
            "details_url": "https://github.com/tenstorrent/tt-metal/actions/runs/18942222369/job/54083837898"
          },
          {
            "name": "ttsim-integration-tests / TTSim Integration - wormhole_b0",
            "status": "COMPLETED",
            "conclusion": "SUCCESS",
            "started_at": "2025-10-30T13:51:23Z",
            "completed_at": "2025-10-30T13:53:49Z",
            "details_url": "https://github.com/tenstorrent/tt-metal/actions/runs/18942222283/job/54085823470"
          },
          {
            "name": "ttsim-integration-tests / TTSim Integration - blackhole",
            "status": "COMPLETED",
            "conclusion": "SUCCESS",
            "started_at": "2025-10-30T13:51:24Z",
            "completed_at": "2025-10-30T13:54:35Z",
            "details_url": "https://github.com/tenstorrent/tt-metal/actions/runs/18942222283/job/54085823484"
          },
          {
            "name": "ttsim-integration-tests / TTNN Pytests - wormhole_b0",
            "status": "COMPLETED",
            "conclusion": "SUCCESS",
            "started_at": "2025-10-30T13:47:10Z",
            "completed_at": "2025-10-30T13:51:42Z",
            "details_url": "https://github.com/tenstorrent/tt-metal/actions/runs/18942222283/job/54085823436"
          },
          {
            "name": "ttsim-integration-tests / TTNN Pytests - blackhole",
            "status": "COMPLETED",
            "conclusion": "SUCCESS",
            "started_at": "2025-10-30T13:47:10Z",
            "completed_at": "2025-10-30T13:52:37Z",
            "details_url": "https://github.com/tenstorrent/tt-metal/actions/runs/18942222283/job/54085823442"
          },
          {
            "name": "build / build-docker-image / \ud83d\udc33\ufe0f Build images",
            "status": "COMPLETED",
            "conclusion": "SKIPPED",
            "started_at": "2025-10-30T13:28:47Z",
            "completed_at": "2025-10-30T13:28:47Z",
            "details_url": "https://github.com/tenstorrent/tt-metal/actions/runs/18942222369/job/54083867133"
          },
          {
            "name": "clang-tidy-light",
            "status": "COMPLETED",
            "conclusion": "SKIPPED",
            "started_at": "2025-10-30T13:27:42Z",
            "completed_at": "2025-10-30T13:27:42Z",
            "details_url": "https://github.com/tenstorrent/tt-metal/actions/runs/18942222283/job/54083755124"
          },
          {
            "name": "build / build-docker-image / \ud83d\udd04 Update latest tag",
            "status": "COMPLETED",
            "conclusion": "SKIPPED",
            "started_at": "2025-10-30T13:28:47Z",
            "completed_at": "2025-10-30T13:28:47Z",
            "details_url": "https://github.com/tenstorrent/tt-metal/actions/runs/18942222369/job/54083867053"
          },
          {
            "name": "build / \ud83d\udee0\ufe0f Build Release ubuntu 22.04",
            "status": "COMPLETED",
            "conclusion": "SUCCESS",
            "started_at": "2025-10-30T13:29:26Z",
            "completed_at": "2025-10-30T13:56:44Z",
            "details_url": "https://github.com/tenstorrent/tt-metal/actions/runs/18942222369/job/54083867874"
          },
          {
            "name": "build / \ud83d\udc0d Build wheel (Python 3.10)",
            "status": "COMPLETED",
            "conclusion": "SUCCESS",
            "started_at": "2025-10-30T13:29:27Z",
            "completed_at": "2025-10-30T13:42:36Z",
            "details_url": "https://github.com/tenstorrent/tt-metal/actions/runs/18942222369/job/54083867909"
          },
          {
            "name": "build-tsan / build-docker-image / check-docker-images",
            "status": "COMPLETED",
            "conclusion": "SUCCESS",
            "started_at": "2025-10-30T13:28:34Z",
            "completed_at": "2025-10-30T13:28:48Z",
            "details_url": "https://github.com/tenstorrent/tt-metal/actions/runs/18942222369/job/54083837795"
          },
          {
            "name": "build-tsan / build-docker-image / \ud83d\udc33\ufe0f Build images",
            "status": "COMPLETED",
            "conclusion": "SKIPPED",
            "started_at": "2025-10-30T13:28:49Z",
            "completed_at": "2025-10-30T13:28:49Z",
            "details_url": "https://github.com/tenstorrent/tt-metal/actions/runs/18942222369/job/54083870731"
          },
          {
            "name": "build-tsan / build-docker-image / \ud83d\udd04 Update latest tag",
            "status": "COMPLETED",
            "conclusion": "SKIPPED",
            "started_at": "2025-10-30T13:28:49Z",
            "completed_at": "2025-10-30T13:28:49Z",
            "details_url": "https://github.com/tenstorrent/tt-metal/actions/runs/18942222369/job/54083870374"
          },
          {
            "name": "build-tsan / \ud83d\udee0\ufe0f Build TSan ubuntu 24.04",
            "status": "COMPLETED",
            "conclusion": "SUCCESS",
            "started_at": "2025-10-30T13:29:28Z",
            "completed_at": "2025-10-30T13:58:22Z",
            "details_url": "https://github.com/tenstorrent/tt-metal/actions/runs/18942222369/job/54083872760"
          },
          {
            "name": "build-tsan / \ud83d\udc0d Build wheel (Python ${{ inputs.version == '22.04' && '3.10' || '3.12' }})",
            "status": "COMPLETED",
            "conclusion": "SKIPPED",
            "started_at": "2025-10-30T13:28:50Z",
            "completed_at": "2025-10-30T13:28:50Z",
            "details_url": "https://github.com/tenstorrent/tt-metal/actions/runs/18942222369/job/54083872374"
          },
          {
            "name": "build-sweeps / build (22.04, cmake/x86_64-linux-clang-17-libstdcpp-toolchain.cmake, Debug) / build-docker-image / check-docker-images",
            "status": "COMPLETED",
            "conclusion": "SUCCESS",
            "started_at": "2025-10-30T13:28:39Z",
            "completed_at": "2025-10-30T13:28:52Z",
            "details_url": "https://github.com/tenstorrent/tt-metal/actions/runs/18942222369/job/54083839626"
          },
          {
            "name": "build-sweeps / build (22.04, cmake/x86_64-linux-clang-17-libstdcpp-toolchain.cmake, Debug) / build-docker-image / \ud83d\udc33\ufe0f Build images",
            "status": "COMPLETED",
            "conclusion": "SKIPPED",
            "started_at": "2025-10-30T13:28:55Z",
            "completed_at": "2025-10-30T13:28:55Z",
            "details_url": "https://github.com/tenstorrent/tt-metal/actions/runs/18942222369/job/54083880934"
          },
          {
            "name": "build-sweeps / build (22.04, cmake/x86_64-linux-clang-17-libstdcpp-toolchain.cmake, Debug) / build-docker-image / \ud83d\udd04 Update latest tag",
            "status": "COMPLETED",
            "conclusion": "SKIPPED",
            "started_at": "2025-10-30T13:28:55Z",
            "completed_at": "2025-10-30T13:28:55Z",
            "details_url": "https://github.com/tenstorrent/tt-metal/actions/runs/18942222369/job/54083881051"
          },
          {
            "name": "build-sweeps / build (22.04, cmake/x86_64-linux-clang-17-libstdcpp-toolchain.cmake, Debug) / \ud83d\udee0\ufe0f Build Debug ubuntu 22.04",
            "status": "COMPLETED",
            "conclusion": "SUCCESS",
            "started_at": "2025-10-30T13:29:37Z",
            "completed_at": "2025-10-30T13:49:42Z",
            "details_url": "https://github.com/tenstorrent/tt-metal/actions/runs/18942222369/job/54083885246"
          },
          {
            "name": "build-sweeps / build (22.04, cmake/x86_64-linux-clang-17-libstdcpp-toolchain.cmake, Debug) / \ud83d\udc0d Build wheel (Python ${{ inputs.version == '22.04' && '3.10' || '3.12' }})",
            "status": "COMPLETED",
            "conclusion": "SKIPPED",
            "started_at": "2025-10-30T13:28:57Z",
            "completed_at": "2025-10-30T13:28:57Z",
            "details_url": "https://github.com/tenstorrent/tt-metal/actions/runs/18942222369/job/54083885116"
          },
          {
            "name": "build-sweeps / build (22.04, cmake/x86_64-linux-clang-17-libcpp-toolchain.cmake, Release) / build-docker-image / check-docker-images",
            "status": "COMPLETED",
            "conclusion": "SUCCESS",
            "started_at": "2025-10-30T13:28:34Z",
            "completed_at": "2025-10-30T13:28:47Z",
            "details_url": "https://github.com/tenstorrent/tt-metal/actions/runs/18942222369/job/54083839657"
          },
          {
            "name": "build-sweeps / build (22.04, cmake/x86_64-linux-clang-17-libcpp-toolchain.cmake, Release) / build-docker-image / \ud83d\udc33\ufe0f Build images",
            "status": "COMPLETED",
            "conclusion": "SKIPPED",
            "started_at": "2025-10-30T13:28:48Z",
            "completed_at": "2025-10-30T13:28:48Z",
            "details_url": "https://github.com/tenstorrent/tt-metal/actions/runs/18942222369/job/54083868555"
          },
          {
            "name": "build-sweeps / build (22.04, cmake/x86_64-linux-clang-17-libcpp-toolchain.cmake, Release) / build-docker-image / \ud83d\udd04 Update latest tag",
            "status": "COMPLETED",
            "conclusion": "SKIPPED",
            "started_at": "2025-10-30T13:28:48Z",
            "completed_at": "2025-10-30T13:28:48Z",
            "details_url": "https://github.com/tenstorrent/tt-metal/actions/runs/18942222369/job/54083868567"
          },
          {
            "name": "build-sweeps / build (22.04, cmake/x86_64-linux-clang-17-libcpp-toolchain.cmake, Release) / \ud83d\udee0\ufe0f Build Release ubuntu 22.04",
            "status": "COMPLETED",
            "conclusion": "SUCCESS",
            "started_at": "2025-10-30T13:29:29Z",
            "completed_at": "2025-10-30T13:49:43Z",
            "details_url": "https://github.com/tenstorrent/tt-metal/actions/runs/18942222369/job/54083869560"
          },
          {
            "name": "build-sweeps / build (22.04, cmake/x86_64-linux-clang-17-libcpp-toolchain.cmake, Release) / \ud83d\udc0d Build wheel (Python ${{ inputs.version == '22.04' && '3.10' || '3.12' }})",
            "status": "COMPLETED",
            "conclusion": "SKIPPED",
            "started_at": "2025-10-30T13:28:48Z",
            "completed_at": "2025-10-30T13:28:48Z",
            "details_url": "https://github.com/tenstorrent/tt-metal/actions/runs/18942222369/job/54083869683"
          },
          {
            "name": "build-sweeps / build (22.04, cmake/x86_64-linux-gcc-12-toolchain.cmake, Release) / build-docker-image / check-docker-images",
            "status": "COMPLETED",
            "conclusion": "SUCCESS",
            "started_at": "2025-10-30T13:28:38Z",
            "completed_at": "2025-10-30T13:28:52Z",
            "details_url": "https://github.com/tenstorrent/tt-metal/actions/runs/18942222369/job/54083839729"
          },
          {
            "name": "build-sweeps / build (22.04, cmake/x86_64-linux-gcc-12-toolchain.cmake, Release) / build-docker-image / \ud83d\udc33\ufe0f Build images",
            "status": "COMPLETED",
            "conclusion": "SKIPPED",
            "started_at": "2025-10-30T13:28:55Z",
            "completed_at": "2025-10-30T13:28:55Z",
            "details_url": "https://github.com/tenstorrent/tt-metal/actions/runs/18942222369/job/54083881193"
          },
          {
            "name": "build-sweeps / build (22.04, cmake/x86_64-linux-gcc-12-toolchain.cmake, Release) / build-docker-image / \ud83d\udd04 Update latest tag",
            "status": "COMPLETED",
            "conclusion": "SKIPPED",
            "started_at": "2025-10-30T13:28:55Z",
            "completed_at": "2025-10-30T13:28:55Z",
            "details_url": "https://github.com/tenstorrent/tt-metal/actions/runs/18942222369/job/54083881289"
          },
          {
            "name": "build-sweeps / build (22.04, cmake/x86_64-linux-gcc-12-toolchain.cmake, Release) / \ud83d\udee0\ufe0f Build Release ubuntu 22.04",
            "status": "COMPLETED",
            "conclusion": "SUCCESS",
            "started_at": "2025-10-30T13:29:38Z",
            "completed_at": "2025-10-30T13:51:15Z",
            "details_url": "https://github.com/tenstorrent/tt-metal/actions/runs/18942222369/job/54083885418"
          },
          {
            "name": "build-sweeps / build (22.04, cmake/x86_64-linux-gcc-12-toolchain.cmake, Release) / \ud83d\udc0d Build wheel (Python ${{ inputs.version == '22.04' && '3.10' || '3.12' }})",
            "status": "COMPLETED",
            "conclusion": "SKIPPED",
            "started_at": "2025-10-30T13:28:57Z",
            "completed_at": "2025-10-30T13:28:57Z",
            "details_url": "https://github.com/tenstorrent/tt-metal/actions/runs/18942222369/job/54083885090"
          },
          {
            "name": "build-sweeps / build (24.04, cmake/x86_64-linux-clang-17-libstdcpp-toolchain.cmake, Release) / build-docker-image / check-docker-images",
            "status": "COMPLETED",
            "conclusion": "SUCCESS",
            "started_at": "2025-10-30T13:28:38Z",
            "completed_at": "2025-10-30T13:28:53Z",
            "details_url": "https://github.com/tenstorrent/tt-metal/actions/runs/18942222369/job/54083839592"
          },
          {
            "name": "build-sweeps / build (24.04, cmake/x86_64-linux-clang-17-libstdcpp-toolchain.cmake, Release) / build-docker-image / \ud83d\udc33\ufe0f Build images",
            "status": "COMPLETED",
            "conclusion": "SKIPPED",
            "started_at": "2025-10-30T13:28:56Z",
            "completed_at": "2025-10-30T13:28:56Z",
            "details_url": "https://github.com/tenstorrent/tt-metal/actions/runs/18942222369/job/54083882111"
          },
          {
            "name": "build-sweeps / build (24.04, cmake/x86_64-linux-clang-17-libstdcpp-toolchain.cmake, Release) / build-docker-image / \ud83d\udd04 Update latest tag",
            "status": "COMPLETED",
            "conclusion": "SKIPPED",
            "started_at": "2025-10-30T13:28:56Z",
            "completed_at": "2025-10-30T13:28:56Z",
            "details_url": "https://github.com/tenstorrent/tt-metal/actions/runs/18942222369/job/54083882353"
          },
          {
            "name": "build-sweeps / build (24.04, cmake/x86_64-linux-clang-17-libstdcpp-toolchain.cmake, Release) / \ud83d\udee0\ufe0f Build Release ubuntu 24.04",
            "status": "COMPLETED",
            "conclusion": "SUCCESS",
            "started_at": "2025-10-30T13:29:39Z",
            "completed_at": "2025-10-30T13:50:02Z",
            "details_url": "https://github.com/tenstorrent/tt-metal/actions/runs/18942222369/job/54083886064"
          },
          {
            "name": "build-sweeps / build (24.04, cmake/x86_64-linux-clang-17-libstdcpp-toolchain.cmake, Release) / \ud83d\udc0d Build wheel (Python ${{ inputs.version == '22.04' && '3.10' || '3.12' }})",
            "status": "COMPLETED",
            "conclusion": "SKIPPED",
            "started_at": "2025-10-30T13:28:58Z",
            "completed_at": "2025-10-30T13:28:58Z",
            "details_url": "https://github.com/tenstorrent/tt-metal/actions/runs/18942222369/job/54083885927"
          },
          {
            "name": "build-sweeps / build (24.04, cmake/x86_64-linux-gcc-14-toolchain.cmake, Release) / build-docker-image / check-docker-images",
            "status": "COMPLETED",
            "conclusion": "SUCCESS",
            "started_at": "2025-10-30T13:28:34Z",
            "completed_at": "2025-10-30T13:28:50Z",
            "details_url": "https://github.com/tenstorrent/tt-metal/actions/runs/18942222369/job/54083839659"
          },
          {
            "name": "build-sweeps / build (24.04, cmake/x86_64-linux-gcc-14-toolchain.cmake, Release) / build-docker-image / \ud83d\udc33\ufe0f Build images",
            "status": "COMPLETED",
            "conclusion": "SKIPPED",
            "started_at": "2025-10-30T13:28:53Z",
            "completed_at": "2025-10-30T13:28:53Z",
            "details_url": "https://github.com/tenstorrent/tt-metal/actions/runs/18942222369/job/54083876525"
          },
          {
            "name": "build-sweeps / build (24.04, cmake/x86_64-linux-gcc-14-toolchain.cmake, Release) / build-docker-image / \ud83d\udd04 Update latest tag",
            "status": "COMPLETED",
            "conclusion": "SKIPPED",
            "started_at": "2025-10-30T13:28:53Z",
            "completed_at": "2025-10-30T13:28:53Z",
            "details_url": "https://github.com/tenstorrent/tt-metal/actions/runs/18942222369/job/54083876709"
          },
          {
            "name": "build-sweeps / build (24.04, cmake/x86_64-linux-gcc-14-toolchain.cmake, Release) / \ud83d\udee0\ufe0f Build Release ubuntu 24.04",
            "status": "COMPLETED",
            "conclusion": "SUCCESS",
            "started_at": "2025-10-30T13:29:37Z",
            "completed_at": "2025-10-30T13:57:08Z",
            "details_url": "https://github.com/tenstorrent/tt-metal/actions/runs/18942222369/job/54083882153"
          },
          {
            "name": "build-sweeps / build (24.04, cmake/x86_64-linux-gcc-14-toolchain.cmake, Release) / \ud83d\udc0d Build wheel (Python ${{ inputs.version == '22.04' && '3.10' || '3.12' }})",
            "status": "COMPLETED",
            "conclusion": "SKIPPED",
            "started_at": "2025-10-30T13:28:56Z",
            "completed_at": "2025-10-30T13:28:55Z",
            "details_url": "https://github.com/tenstorrent/tt-metal/actions/runs/18942222369/job/54083882116"
          },
          {
            "name": "build-asan / build-docker-image / check-docker-images",
            "status": "COMPLETED",
            "conclusion": "SUCCESS",
            "started_at": "2025-10-30T13:28:34Z",
            "completed_at": "2025-10-30T13:28:47Z",
            "details_url": "https://github.com/tenstorrent/tt-metal/actions/runs/18942222369/job/54083837735"
          },
          {
            "name": "build-asan / build-docker-image / \ud83d\udc33\ufe0f Build images",
            "status": "COMPLETED",
            "conclusion": "SKIPPED",
            "started_at": "2025-10-30T13:28:48Z",
            "completed_at": "2025-10-30T13:28:48Z",
            "details_url": "https://github.com/tenstorrent/tt-metal/actions/runs/18942222369/job/54083868251"
          },
          {
            "name": "build-asan / build-docker-image / \ud83d\udd04 Update latest tag",
            "status": "COMPLETED",
            "conclusion": "SKIPPED",
            "started_at": "2025-10-30T13:28:48Z",
            "completed_at": "2025-10-30T13:28:48Z",
            "details_url": "https://github.com/tenstorrent/tt-metal/actions/runs/18942222369/job/54083868505"
          },
          {
            "name": "build-asan / \ud83d\udee0\ufe0f Build ASan ubuntu 22.04",
            "status": "IN_PROGRESS",
            "conclusion": null,
            "started_at": "2025-10-30T13:29:28Z",
            "completed_at": null,
            "details_url": "https://github.com/tenstorrent/tt-metal/actions/runs/18942222369/job/54083869604"
          },
          {
            "name": "build-asan / \ud83d\udc0d Build wheel (Python ${{ inputs.version == '22.04' && '3.10' || '3.12' }})",
            "status": "COMPLETED",
            "conclusion": "SKIPPED",
            "started_at": "2025-10-30T13:28:48Z",
            "completed_at": "2025-10-30T13:28:48Z",
            "details_url": "https://github.com/tenstorrent/tt-metal/actions/runs/18942222369/job/54083869769"
          },
          {
            "name": "build-docs / build-docs",
            "status": "COMPLETED",
            "conclusion": "SUCCESS",
            "started_at": "2025-10-30T13:57:42Z",
            "completed_at": "2025-10-30T14:01:20Z",
            "details_url": "https://github.com/tenstorrent/tt-metal/actions/runs/18942222369/job/54086953115"
          },
          {
            "name": "build-docs / deploy-docs",
            "status": "COMPLETED",
            "conclusion": "SKIPPED",
            "started_at": "2025-10-30T14:01:28Z",
            "completed_at": "2025-10-30T14:01:28Z",
            "details_url": "https://github.com/tenstorrent/tt-metal/actions/runs/18942222369/job/54087380240"
          },
          {
            "name": "metalium-smoke-tests (N300-viommu) / smoke",
            "status": "IN_PROGRESS",
            "conclusion": null,
            "started_at": "2025-10-30T14:03:30Z",
            "completed_at": null,
            "details_url": "https://github.com/tenstorrent/tt-metal/actions/runs/18942222369/job/54087059269"
          },
          {
            "name": "metalium-smoke-tests (N300-llmbox-viommu) / smoke",
            "status": "QUEUED",
            "conclusion": null,
            "started_at": "2025-10-30T13:58:32Z",
            "completed_at": null,
            "details_url": "https://github.com/tenstorrent/tt-metal/actions/runs/18942222369/job/54087059290"
          },
          {
            "name": "ttnn-smoke-tests (N300-viommu) / smoke",
            "status": "IN_PROGRESS",
            "conclusion": null,
            "started_at": "2025-10-30T14:03:35Z",
            "completed_at": null,
            "details_url": "https://github.com/tenstorrent/tt-metal/actions/runs/18942222369/job/54087059234"
          }
        ]
      }
    },
    {
      "position": 2,
      "state": "AWAITING_CHECKS",
      "pr_number": 31192,
      "pr_title": "Migrating the rest of (non perf) Gemma3 tests to CIv2 from CIv1",
      "pr_url": "https://github.com/tenstorrent/tt-metal/pull/31192",
      "author": "mstojkoTT",
      "enqueued_at": "2025-10-30T13:41:19Z",
      "estimated_time_to_merge_seconds": 7296,
      "time_in_queue": "23 minutes",
      "commit": {
        "sha": "c425c7047bca0e9eddc2623ab60e632c226bb66b",
        "url": "https://github.com/tenstorrent/tt-metal/commit/c425c7047bca0e9eddc2623ab60e632c226bb66b"
      },
      "ci_status": {
        "overall_state": "PENDING",
        "ci_started_at": "2025-10-30T13:41:38Z",
        "total_checks": 57,
        "running": 2,
        "completed": 55,
        "queued": 0,
        "checks": [
          {
            "name": "static-checks / find-changed-files",
            "status": "COMPLETED",
            "conclusion": "SUCCESS",
            "started_at": "2025-10-30T13:41:42Z",
            "completed_at": "2025-10-30T13:42:25Z",
            "details_url": "https://github.com/tenstorrent/tt-metal/actions/runs/18942654645/job/54085235650"
          },
          {
            "name": "asan-build / build-docker-image / check-docker-images",
            "status": "COMPLETED",
            "conclusion": "SUCCESS",
            "started_at": "2025-10-30T13:41:42Z",
            "completed_at": "2025-10-30T13:41:56Z",
            "details_url": "https://github.com/tenstorrent/tt-metal/actions/runs/18942654587/job/54085235418"
          },
          {
            "name": "find-changed-files",
            "status": "COMPLETED",
            "conclusion": "SUCCESS",
            "started_at": "2025-10-30T13:41:41Z",
            "completed_at": "2025-10-30T13:42:25Z",
            "details_url": "https://github.com/tenstorrent/tt-metal/actions/runs/18942654476/job/54085233892"
          },
          {
            "name": "asan-build / build-docker-image / \ud83d\udc33\ufe0f Build images",
            "status": "COMPLETED",
            "conclusion": "SKIPPED",
            "started_at": "2025-10-30T13:41:57Z",
            "completed_at": "2025-10-30T13:41:56Z",
            "details_url": "https://github.com/tenstorrent/tt-metal/actions/runs/18942654587/job/54085268257"
          },
          {
            "name": "static-checks / Run Pre-commit Hooks",
            "status": "COMPLETED",
            "conclusion": "SUCCESS",
            "started_at": "2025-10-30T13:41:42Z",
            "completed_at": "2025-10-30T13:42:38Z",
            "details_url": "https://github.com/tenstorrent/tt-metal/actions/runs/18942654645/job/54085235664"
          },
          {
            "name": "Run Pre-commit Hooks",
            "status": "COMPLETED",
            "conclusion": "SUCCESS",
            "started_at": "2025-10-30T13:41:40Z",
            "completed_at": "2025-10-30T13:42:33Z",
            "details_url": "https://github.com/tenstorrent/tt-metal/actions/runs/18942654476/job/54085233890"
          },
          {
            "name": "asan-build / build-docker-image / \ud83d\udd04 Update latest tag",
            "status": "COMPLETED",
            "conclusion": "SKIPPED",
            "started_at": "2025-10-30T13:41:57Z",
            "completed_at": "2025-10-30T13:41:56Z",
            "details_url": "https://github.com/tenstorrent/tt-metal/actions/runs/18942654587/job/54085268116"
          },
          {
            "name": "static-checks / check-black",
            "status": "COMPLETED",
            "conclusion": "SUCCESS",
            "started_at": "2025-10-30T13:41:42Z",
            "completed_at": "2025-10-30T13:41:45Z",
            "details_url": "https://github.com/tenstorrent/tt-metal/actions/runs/18942654645/job/54085235566"
          },
          {
            "name": "check-black",
            "status": "COMPLETED",
            "conclusion": "SUCCESS",
            "started_at": "2025-10-30T13:41:40Z",
            "completed_at": "2025-10-30T13:41:42Z",
            "details_url": "https://github.com/tenstorrent/tt-metal/actions/runs/18942654476/job/54085233979"
          },
          {
            "name": "asan-build / \ud83d\udee0\ufe0f Build ASanCoverage ubuntu 22.04",
            "status": "IN_PROGRESS",
            "conclusion": null,
            "started_at": "2025-10-30T13:51:43Z",
            "completed_at": null,
            "details_url": "https://github.com/tenstorrent/tt-metal/actions/runs/18942654587/job/54085268280"
          },
          {
            "name": "static-checks / check-spdx-licenses",
            "status": "COMPLETED",
            "conclusion": "SUCCESS",
            "started_at": "2025-10-30T13:41:42Z",
            "completed_at": "2025-10-30T13:42:50Z",
            "details_url": "https://github.com/tenstorrent/tt-metal/actions/runs/18942654645/job/54085235666"
          },
          {
            "name": "check-spdx-licenses",
            "status": "COMPLETED",
            "conclusion": "SUCCESS",
            "started_at": "2025-10-30T13:41:39Z",
            "completed_at": "2025-10-30T13:42:45Z",
            "details_url": "https://github.com/tenstorrent/tt-metal/actions/runs/18942654476/job/54085233909"
          },
          {
            "name": "asan-build / \ud83d\udc0d Build wheel (Python ${{ inputs.version == '22.04' && '3.10' || '3.12' }})",
            "status": "COMPLETED",
            "conclusion": "SKIPPED",
            "started_at": "2025-10-30T13:41:57Z",
            "completed_at": "2025-10-30T13:41:57Z",
            "details_url": "https://github.com/tenstorrent/tt-metal/actions/runs/18942654587/job/54085268629"
          },
          {
            "name": "static-checks / check-metal-kernel-count",
            "status": "COMPLETED",
            "conclusion": "SUCCESS",
            "started_at": "2025-10-30T13:41:42Z",
            "completed_at": "2025-10-30T13:41:51Z",
            "details_url": "https://github.com/tenstorrent/tt-metal/actions/runs/18942654645/job/54085235603"
          },
          {
            "name": "check-metal-kernel-count",
            "status": "COMPLETED",
            "conclusion": "SUCCESS",
            "started_at": "2025-10-30T13:41:41Z",
            "completed_at": "2025-10-30T13:41:51Z",
            "details_url": "https://github.com/tenstorrent/tt-metal/actions/runs/18942654476/job/54085234156"
          },
          {
            "name": "static-checks / check-doc",
            "status": "COMPLETED",
            "conclusion": "SUCCESS",
            "started_at": "2025-10-30T13:41:42Z",
            "completed_at": "2025-10-30T13:42:11Z",
            "details_url": "https://github.com/tenstorrent/tt-metal/actions/runs/18942654645/job/54085235618"
          },
          {
            "name": "find-changed-files",
            "status": "COMPLETED",
            "conclusion": "SUCCESS",
            "started_at": "2025-10-30T13:41:42Z",
            "completed_at": "2025-10-30T13:42:24Z",
            "details_url": "https://github.com/tenstorrent/tt-metal/actions/runs/18942654587/job/54085235150"
          },
          {
            "name": "check-doc",
            "status": "COMPLETED",
            "conclusion": "SUCCESS",
            "started_at": "2025-10-30T13:41:41Z",
            "completed_at": "2025-10-30T13:43:32Z",
            "details_url": "https://github.com/tenstorrent/tt-metal/actions/runs/18942654476/job/54085234112"
          },
          {
            "name": "static-checks / check-forbidden-imports",
            "status": "COMPLETED",
            "conclusion": "SUCCESS",
            "started_at": "2025-10-30T13:41:42Z",
            "completed_at": "2025-10-30T13:41:51Z",
            "details_url": "https://github.com/tenstorrent/tt-metal/actions/runs/18942654645/job/54085235613"
          },
          {
            "name": "build / build-docker-image / check-docker-images",
            "status": "COMPLETED",
            "conclusion": "SUCCESS",
            "started_at": "2025-10-30T13:41:42Z",
            "completed_at": "2025-10-30T13:41:54Z",
            "details_url": "https://github.com/tenstorrent/tt-metal/actions/runs/18942654587/job/54085235421"
          },
          {
            "name": "check-forbidden-imports",
            "status": "COMPLETED",
            "conclusion": "SUCCESS",
            "started_at": "2025-10-30T13:41:41Z",
            "completed_at": "2025-10-30T13:41:54Z",
            "details_url": "https://github.com/tenstorrent/tt-metal/actions/runs/18942654476/job/54085234167"
          },
          {
            "name": "build / build-docker-image / \ud83d\udc33\ufe0f Build images",
            "status": "COMPLETED",
            "conclusion": "SKIPPED",
            "started_at": "2025-10-30T13:41:55Z",
            "completed_at": "2025-10-30T13:41:54Z",
            "details_url": "https://github.com/tenstorrent/tt-metal/actions/runs/18942654587/job/54085264415"
          },
          {
            "name": "static-checks / check-interleaved-addr-gen-usage",
            "status": "COMPLETED",
            "conclusion": "SUCCESS",
            "started_at": "2025-10-30T13:41:43Z",
            "completed_at": "2025-10-30T13:42:24Z",
            "details_url": "https://github.com/tenstorrent/tt-metal/actions/runs/18942654645/job/54085235544"
          },
          {
            "name": "check-interleaved-addr-gen-usage",
            "status": "COMPLETED",
            "conclusion": "SUCCESS",
            "started_at": "2025-10-30T13:41:41Z",
            "completed_at": "2025-10-30T13:42:23Z",
            "details_url": "https://github.com/tenstorrent/tt-metal/actions/runs/18942654476/job/54085234158"
          },
          {
            "name": "build / build-docker-image / \ud83d\udd04 Update latest tag",
            "status": "COMPLETED",
            "conclusion": "SKIPPED",
            "started_at": "2025-10-30T13:41:55Z",
            "completed_at": "2025-10-30T13:41:54Z",
            "details_url": "https://github.com/tenstorrent/tt-metal/actions/runs/18942654587/job/54085264515"
          },
          {
            "name": "static-checks / check-sweeps-workflow",
            "status": "COMPLETED",
            "conclusion": "SUCCESS",
            "started_at": "2025-10-30T13:41:43Z",
            "completed_at": "2025-10-30T13:41:57Z",
            "details_url": "https://github.com/tenstorrent/tt-metal/actions/runs/18942654645/job/54085235605"
          },
          {
            "name": "check-sweeps-workflow",
            "status": "COMPLETED",
            "conclusion": "SUCCESS",
            "started_at": "2025-10-30T13:41:41Z",
            "completed_at": "2025-10-30T13:41:55Z",
            "details_url": "https://github.com/tenstorrent/tt-metal/actions/runs/18942654476/job/54085234162"
          },
          {
            "name": "build / \ud83d\udee0\ufe0f Build Release ubuntu 22.04",
            "status": "IN_PROGRESS",
            "conclusion": null,
            "started_at": "2025-10-30T13:51:03Z",
            "completed_at": null,
            "details_url": "https://github.com/tenstorrent/tt-metal/actions/runs/18942654587/job/54085264508"
          },
          {
            "name": "static-checks / cmake-version",
            "status": "COMPLETED",
            "conclusion": "SUCCESS",
            "started_at": "2025-10-30T13:41:42Z",
            "completed_at": "2025-10-30T13:42:49Z",
            "details_url": "https://github.com/tenstorrent/tt-metal/actions/runs/18942654645/job/54085235697"
          },
          {
            "name": "cmake-version",
            "status": "COMPLETED",
            "conclusion": "SUCCESS",
            "started_at": "2025-10-30T13:41:41Z",
            "completed_at": "2025-10-30T13:42:53Z",
            "details_url": "https://github.com/tenstorrent/tt-metal/actions/runs/18942654476/job/54085234206"
          },
          {
            "name": "static-checks / codeowners-validator",
            "status": "COMPLETED",
            "conclusion": "SUCCESS",
            "started_at": "2025-10-30T13:41:42Z",
            "completed_at": "2025-10-30T13:41:52Z",
            "details_url": "https://github.com/tenstorrent/tt-metal/actions/runs/18942654645/job/54085235568"
          },
          {
            "name": "build / \ud83d\udc0d Build wheel (Python 3.10)",
            "status": "COMPLETED",
            "conclusion": "SUCCESS",
            "started_at": "2025-10-30T13:50:58Z",
            "completed_at": "2025-10-30T14:03:00Z",
            "details_url": "https://github.com/tenstorrent/tt-metal/actions/runs/18942654587/job/54085264522"
          },
          {
            "name": "codeowners-validator",
            "status": "COMPLETED",
            "conclusion": "SUCCESS",
            "started_at": "2025-10-30T13:41:40Z",
            "completed_at": "2025-10-30T13:41:51Z",
            "details_url": "https://github.com/tenstorrent/tt-metal/actions/runs/18942654476/job/54085234190"
          },
          {
            "name": "docker-image",
            "status": "COMPLETED",
            "conclusion": "SKIPPED",
            "started_at": "2025-10-30T13:41:38Z",
            "completed_at": "2025-10-30T13:41:38Z",
            "details_url": "https://github.com/tenstorrent/tt-metal/actions/runs/18942654587/job/54085235220"
          },
          {
            "name": "static-checks / check-symlinks-valid",
            "status": "COMPLETED",
            "conclusion": "SUCCESS",
            "started_at": "2025-10-30T13:41:42Z",
            "completed_at": "2025-10-30T13:41:51Z",
            "details_url": "https://github.com/tenstorrent/tt-metal/actions/runs/18942654645/job/54085235699"
          },
          {
            "name": "check-symlinks-valid",
            "status": "COMPLETED",
            "conclusion": "SUCCESS",
            "started_at": "2025-10-30T13:41:41Z",
            "completed_at": "2025-10-30T13:41:51Z",
            "details_url": "https://github.com/tenstorrent/tt-metal/actions/runs/18942654476/job/54085234177"
          },
          {
            "name": "static-checks / check-docs-links",
            "status": "COMPLETED",
            "conclusion": "SKIPPED",
            "started_at": "2025-10-30T13:42:25Z",
            "completed_at": "2025-10-30T13:42:25Z",
            "details_url": "https://github.com/tenstorrent/tt-metal/actions/runs/18942654645/job/54085318106"
          },
          {
            "name": "check-docs-links",
            "status": "COMPLETED",
            "conclusion": "SKIPPED",
            "started_at": "2025-10-30T13:42:25Z",
            "completed_at": "2025-10-30T13:42:25Z",
            "details_url": "https://github.com/tenstorrent/tt-metal/actions/runs/18942654476/job/54085317722"
          },
          {
            "name": "code-analysis / determine-scan-type",
            "status": "COMPLETED",
            "conclusion": "SUCCESS",
            "started_at": "2025-10-30T13:41:43Z",
            "completed_at": "2025-10-30T13:42:30Z",
            "details_url": "https://github.com/tenstorrent/tt-metal/actions/runs/18942654645/job/54085235599"
          },
          {
            "name": "code-analysis / build-docker-image / check-docker-images",
            "status": "COMPLETED",
            "conclusion": "SUCCESS",
            "started_at": "2025-10-30T13:41:42Z",
            "completed_at": "2025-10-30T13:41:53Z",
            "details_url": "https://github.com/tenstorrent/tt-metal/actions/runs/18942654645/job/54085235708"
          },
          {
            "name": "code-analysis / build-docker-image / \ud83d\udc33\ufe0f Build images",
            "status": "COMPLETED",
            "conclusion": "SKIPPED",
            "started_at": "2025-10-30T13:41:54Z",
            "completed_at": "2025-10-30T13:41:54Z",
            "details_url": "https://github.com/tenstorrent/tt-metal/actions/runs/18942654645/job/54085262956"
          },
          {
            "name": "code-analysis / build-docker-image / \ud83d\udd04 Update latest tag",
            "status": "COMPLETED",
            "conclusion": "SKIPPED",
            "started_at": "2025-10-30T13:41:54Z",
            "completed_at": "2025-10-30T13:41:54Z",
            "details_url": "https://github.com/tenstorrent/tt-metal/actions/runs/18942654645/job/54085263249"
          },
          {
            "name": "model-charts-sync",
            "status": "COMPLETED",
            "conclusion": "SKIPPED",
            "started_at": "2025-10-30T13:42:25Z",
            "completed_at": "2025-10-30T13:42:25Z",
            "details_url": "https://github.com/tenstorrent/tt-metal/actions/runs/18942654587/job/54085317267"
          },
          {
            "name": "code-analysis / \ud83e\udd16 Clang Tidy",
            "status": "COMPLETED",
            "conclusion": "SKIPPED",
            "started_at": "2025-10-30T13:42:30Z",
            "completed_at": "2025-10-30T13:42:30Z",
            "details_url": "https://github.com/tenstorrent/tt-metal/actions/runs/18942654645/job/54085327070"
          },
          {
            "name": "find-changes",
            "status": "COMPLETED",
            "conclusion": "SUCCESS",
            "started_at": "2025-10-30T13:41:42Z",
            "completed_at": "2025-10-30T13:42:25Z",
            "details_url": "https://github.com/tenstorrent/tt-metal/actions/runs/18942654645/job/54085235563"
          },
          {
            "name": "fail-fast",
            "status": "COMPLETED",
            "conclusion": "SKIPPED",
            "started_at": "2025-10-30T13:42:30Z",
            "completed_at": "2025-10-30T13:42:30Z",
            "details_url": "https://github.com/tenstorrent/tt-metal/actions/runs/18942654645/job/54085327252"
          },
          {
            "name": "build",
            "status": "COMPLETED",
            "conclusion": "SKIPPED",
            "started_at": "2025-10-30T13:42:26Z",
            "completed_at": "2025-10-30T13:42:25Z",
            "details_url": "https://github.com/tenstorrent/tt-metal/actions/runs/18942654645/job/54085318657"
          },
          {
            "name": "clang-tidy-light",
            "status": "COMPLETED",
            "conclusion": "SKIPPED",
            "started_at": "2025-10-30T13:41:38Z",
            "completed_at": "2025-10-30T13:41:38Z",
            "details_url": "https://github.com/tenstorrent/tt-metal/actions/runs/18942654587/job/54085235855"
          },
          {
            "name": "build-tsan",
            "status": "COMPLETED",
            "conclusion": "SKIPPED",
            "started_at": "2025-10-30T13:42:26Z",
            "completed_at": "2025-10-30T13:42:25Z",
            "details_url": "https://github.com/tenstorrent/tt-metal/actions/runs/18942654645/job/54085318608"
          },
          {
            "name": "build-sweeps",
            "status": "COMPLETED",
            "conclusion": "SKIPPED",
            "started_at": "2025-10-30T13:42:26Z",
            "completed_at": "2025-10-30T13:42:25Z",
            "details_url": "https://github.com/tenstorrent/tt-metal/actions/runs/18942654645/job/54085318560"
          },
          {
            "name": "build-asan",
            "status": "COMPLETED",
            "conclusion": "SKIPPED",
            "started_at": "2025-10-30T13:42:25Z",
            "completed_at": "2025-10-30T13:42:25Z",
            "details_url": "https://github.com/tenstorrent/tt-metal/actions/runs/18942654645/job/54085318409"
          },
          {
            "name": "build-docs",
            "status": "COMPLETED",
            "conclusion": "SKIPPED",
            "started_at": "2025-10-30T13:42:26Z",
            "completed_at": "2025-10-30T13:42:25Z",
            "details_url": "https://github.com/tenstorrent/tt-metal/actions/runs/18942654645/job/54085318533"
          },
          {
            "name": "metalium-smoke-tests",
            "status": "COMPLETED",
            "conclusion": "SKIPPED",
            "started_at": "2025-10-30T13:42:26Z",
            "completed_at": "2025-10-30T13:42:25Z",
            "details_url": "https://github.com/tenstorrent/tt-metal/actions/runs/18942654645/job/54085318715"
          },
          {
            "name": "ttnn-smoke-tests",
            "status": "COMPLETED",
            "conclusion": "SKIPPED",
            "started_at": "2025-10-30T13:42:26Z",
            "completed_at": "2025-10-30T13:42:25Z",
            "details_url": "https://github.com/tenstorrent/tt-metal/actions/runs/18942654645/job/54085318831"
          },
          {
            "name": "metalium-basic-tests",
            "status": "COMPLETED",
            "conclusion": "SKIPPED",
            "started_at": "2025-10-30T13:42:26Z",
            "completed_at": "2025-10-30T13:42:25Z",
            "details_url": "https://github.com/tenstorrent/tt-metal/actions/runs/18942654645/job/54085318748"
          },
          {
            "name": "ttnn-basic-tests",
            "status": "COMPLETED",
            "conclusion": "SKIPPED",
            "started_at": "2025-10-30T13:42:26Z",
            "completed_at": "2025-10-30T13:42:25Z",
            "details_url": "https://github.com/tenstorrent/tt-metal/actions/runs/18942654645/job/54085318617"
          },
          {
            "name": "Merge Gate Status",
            "status": "COMPLETED",
            "conclusion": "SUCCESS",
            "started_at": "2025-10-30T13:42:54Z",
            "completed_at": "2025-10-30T13:43:02Z",
            "details_url": "https://github.com/tenstorrent/tt-metal/actions/runs/18942654645/job/54085360782"
          }
        ]
      }
    }
  ]
}